hatch_sphinx/__init__.py
hatch_sphinx/_version.py
hatch_sphinx/hooks.py
hatch_sphinx/plugin.py
hatch_sphinx/py.typed
hatch_sphinx-0.0.4.dist-info/METADATA
hatch_sphinx-0.0.4.dist-info/WHEEL
hatch_sphinx-0.0.4.dist-info/entry_points.txt
hatch_sphinx-0.0.4.dist-info/licenses/LICENSE
hatch_sphinx-0.0.4.dist-info/RECORD
