Metadata-Version: 2.4
Name: hatch-sphinx
Version: 0.0.4
Summary: A plugin for Hatch for building documentation with Sphinx
Project-URL: Documentation, https://github.com/llimeht/hatch-sphinx#readme
Project-URL: Issues, https://github.com/llimeht/hatch-sphinx/issues
Project-URL: Source, https://github.com/llimeht/hatch-sphinx
Author-email: Stuart Prescott <stuart@debian.org>
License-Expression: MIT
License-File: LICENSE
Classifier: Development Status :: 4 - Beta
Classifier: Framework :: Hatch
Classifier: Programming Language :: Python
Classifier: Programming Language :: Python :: 3.9
Classifier: Programming Language :: Python :: 3.10
Classifier: Programming Language :: Python :: 3.11
Classifier: Programming Language :: Python :: 3.12
Classifier: Programming Language :: Python :: 3.13
Classifier: Programming Language :: Python :: Implementation :: CPython
Classifier: Programming Language :: Python :: Implementation :: PyPy
Requires-Python: >=3.9
Requires-Dist: hatchling
Requires-Dist: sphinx
